{
    "configurations": [
        {
            "name": "Win32",
            "includePath": [
                "C:\\Users\\ProBook\\AppData\\Local\\Arduino15\\packages\\esp8266\\tools\\**",
                "C:\\Users\\ProBook\\AppData\\Local\\Arduino15\\packages\\esp8266\\hardware\\esp8266\\2.5.0\\**",
                "${workspaceFolder}/**",
                "${workspaceFolder}/src/**",
                "${workspaceFolder}/webserver/**"
            ],
            "defines": [
                "_DEBUG",
                "UNICODE",
                "_UNICODE",
                "ARDUINO"
            ],
            "windowsSdkVersion": "10.0.16299.0",
            "compilerPath": "C:/Program Files (x86)/Microsoft Visual Studio/2017/Community/VC/Tools/MSVC/14.13.26128/bin/Hostx64/x64/cl.exe",
            "cStandard": "c11",
            "cppStandard": "c++17",
            "intelliSenseMode": "msvc-x64",
            "forcedInclude": []
        }
    ],
    "version": 4
}